{
  "project_info": {
    "project_number": "79320588047",
    "firebase_url": "https://classassistant-fa6d2.firebaseio.com",
    "project_id": "classassistant-fa6d2",
    "storage_bucket": "classassistant-fa6d2.appspot.com"
  },
  "client": [
    {
      "client_info": {
        "mobilesdk_app_id": "1:79320588047:android:be99c5d39cce55cb",
        "android_client_info": {
          "package_name": "com.example.chandnimittal.classassistant"
        }
      },
      "oauth_client": [
        {
          "client_id": "79320588047-tj1egjtpds26atil058f9hchfdp02dka.apps.googleusercontent.com",
          "client_type": 3
        }
      ],
      "api_key": [
        {
          "current_key": "AIzaSyDFRLOVOElmwHb2sm9qj1eiiwcUOLpSceg"
        }
      ],
      "services": {
        "analytics_service": {
          "status": 1
        },
        "appinvite_service": {
          "status": 1,
          "other_platform_oauth_client": []
        },
        "ads_service": {
          "status": 2
        }
      }
    }
  ],
  "configuration_version": "1"
}